README.rst
flask_indieauth.py
setup.py
Flask_IndieAuth.egg-info/PKG-INFO
Flask_IndieAuth.egg-info/SOURCES.txt
Flask_IndieAuth.egg-info/dependency_links.txt
Flask_IndieAuth.egg-info/not-zip-safe
Flask_IndieAuth.egg-info/requires.txt
Flask_IndieAuth.egg-info/top_level.txt